Workbook

Sheet Rate Card
A1: Module 8 — Cost Model · Rate Card
A2: Edit the BLUE cells. Rates are illustrative (~Premium, 2025) and CHANGE — verify against the Databricks pricing page and your cloud bill.
A4: Databricks DBU rates ($ per DBU-hour)
A5: All-purpose compute | B5: 0.55 | C5: interactive; ~2x jobs
A6: Job compute | B6: 0.3 | C6: automated runs — the default
A7: Serverless (blended) | B7: 0.35 | C7: folds VM in; no separate VM bill
A8: Jobs light | B8: 0.22 | C8: simple jobs
A9: Serverless SQL | B9: 0.7 | C9: BI queries
A11: Cloud compute & commitments
A12: VM $ per node-hour (on-demand) | B12: 0.096 | C12: e.g. m5.large-class node
A13: DBUs per node-hour | B13: 1 | C13: instance-dependent
A14: Spot discount (off VM price) | B14: 0.7 | C14: up to ~90%; fault-tolerant only
A15: Reserved discount (off VM price) | B15: 0.4 | C15: 1–3 yr commitment
A17: Storage ($/GB-month) & network
A18: Storage — hot | B18: 0.023
A19: Storage — cool | B19: 0.013
A20: Storage — archive | B20: 0.001 | C20: ~23x cheaper than hot
A21: Egress $ per GB | B21: 0.09 | C21: data OUT to internet; first ~100GB free

Sheet Cost Model
A1: Cost Model · one workload → monthly TCO
A2: Edit BLUE inputs. GREEN cells link to the Rate Card. Black cells are computed.
A4: Workload inputs
A5: Runtime per run (minutes) | B5: 40
A6: Nodes | B6: 8
A7: Runs per month | B7: 30 | C7: e.g. 30 for nightly
A8: DBU rate ($/DBU-hr) | B8: ='Rate Card'!B6 -> 0.3 | C8: links Rate Card (default = Job compute; point to another family to compare)
A9: Purchase (1=on-demand, 2=spot, 3=reserved) | B9: 1
A11: Compute
A12: Runtime (hours) | B12: =B5/60 -> 0.66666667
A13: VM $/node-hr (after purchase option) | B13: ='Rate Card'!B12*IF(B9=2,1-'Rate Card'!B14,IF(B9=3,1-'Rate Card'!B15,1)) -> 0.096
A14: Databricks DBU cost / run | B14: =B6*'Rate Card'!B13*B8*B12 -> 1.6
A15: Cloud VM cost / run | B15: =B6*B13*B12 -> 0.512
A16: Total / run | B16: =B14+B15 -> 2.112
A17: Compute / month | B17: =B16*B7 -> 63.36
A19: Storage
A20: Storage — hot (GB) | B20: 50000
A21: Storage — cool (GB) | B21: 0
A22: Storage — archive (GB) | B22: 0
A23: Storage / month | B23: =B20*'Rate Card'!B18+B21*'Rate Card'!B19+B22*'Rate Card'!B20 -> 1150
A25: Network & other
A26: Egress (GB / month) | B26: 2000
A27: Egress / month | B27: =B26*'Rate Card'!B21 -> 180
A28: Other / month (managed premium, logging, …) | B28: 0
A30: TOTAL MONTHLY COST | B30: =B17+B23+B27+B28 -> 1393.36
A31: TOTAL ANNUAL COST | B31: =B30*12 -> 16720.32

Sheet Scenarios
A1: Scenarios · same workload, priced four ways
A2: Uses the runtime / nodes / runs from the Cost Model sheet. Lowest monthly wins (subject to the SLA + spot risk).
A4: Scenario | B4: DBU rate | C4: VM factor | D4: Total / run | E4: Per month
A5: Job compute — on-demand | B5: ='Rate Card'!B6 -> 0.3 | C5: 1 | D5: ='Cost Model'!B6*'Rate Card'!B13*B5*'Cost Model'!B12+'Cost Model'!B6*'Rate Card'!B12*C5*'Cost Model'!B12 -> 2.112 | E5: =D5*'Cost Model'!B7 -> 63.36
A6: Job compute — spot | B6: ='Rate Card'!B6 -> 0.3 | C6: =1-'Rate Card'!B14 -> 0.3 | D6: ='Cost Model'!B6*'Rate Card'!B13*B6*'Cost Model'!B12+'Cost Model'!B6*'Rate Card'!B12*C6*'Cost Model'!B12 -> 1.7536 | E6: =D6*'Cost Model'!B7 -> 52.608
A7: Serverless (no VM bill) | B7: ='Rate Card'!B7 -> 0.35 | C7: 0 | D7: ='Cost Model'!B6*'Rate Card'!B13*B7*'Cost Model'!B12+'Cost Model'!B6*'Rate Card'!B12*C7*'Cost Model'!B12 -> 1.8666667 | E7: =D7*'Cost Model'!B7 -> 56
A8: All-purpose — on-demand | B8: ='Rate Card'!B5 -> 0.55 | C8: 1 | D8: ='Cost Model'!B6*'Rate Card'!B13*B8*'Cost Model'!B12+'Cost Model'!B6*'Rate Card'!B12*C8*'Cost Model'!B12 -> 3.4453333 | E8: =D8*'Cost Model'!B7 -> 103.36
A10: Cheapest / month | E10: =MIN(E5:E9) -> 52.608

Sheet SLA Tradeoff
A1: Cost vs SLA · cheapest config that meets the deadline
A2: More nodes finish faster. Under ideal scaling, TOTAL cost is ~flat (same node-hours) — pick the cheapest that MEETS the SLA.
A4: Total work (node-hours) | B4: 4 | C4: from a benchmark
A5: Deadline (minutes) | B5: 60 | C5: the SLA
A6: DBU rate ($/DBU-hr) | B6: ='Rate Card'!B6 -> 0.3
A7: VM factor (1=on-demand) | B7: 1
A9: Nodes | B9: Runtime (min) | C9: Total / run | D9: Meets SLA?
A10: 2 | B10: =$B$4/A10*60 -> 120 | C10: =A10*'Rate Card'!B13*$B$6*($B$4/A10)+A10*'Rate Card'!B12*$B$7*($B$4/A10) -> 1.584 | D10: =IF(B10<=$B$5,"YES","no") -> no
A11: 4 | B11: =$B$4/A11*60 -> 60 | C11: =A11*'Rate Card'!B13*$B$6*($B$4/A11)+A11*'Rate Card'!B12*$B$7*($B$4/A11) -> 1.584 | D11: =IF(B11<=$B$5,"YES","no") -> YES
A12: 8 | B12: =$B$4/A12*60 -> 30 | C12: =A12*'Rate Card'!B13*$B$6*($B$4/A12)+A12*'Rate Card'!B12*$B$7*($B$4/A12) -> 1.584 | D12: =IF(B12<=$B$5,"YES","no") -> YES
A13: 16 | B13: =$B$4/A13*60 -> 15 | C13: =A13*'Rate Card'!B13*$B$6*($B$4/A13)+A13*'Rate Card'!B12*$B$7*($B$4/A13) -> 1.584 | D13: =IF(B13<=$B$5,"YES","no") -> YES

Sheet Hidden-Cost Checklist
A1: Hidden-Cost Checklist · tick before you present
A2: Check each before finalizing your cost model — these are where real bills hide.
A3: ✓ | B3: Check | C3: Your note
A4: ☐ | B4: Scheduled work moved OFF all-purpose to job/serverless clusters
A5: ☐ | B5: Auto-termination set on every cluster
A6: ☐ | B6: Spot used only for fault-tolerant, checkpointed work (and the SLA risk accepted)
A7: ☐ | B7: Reserved/savings only for the predictable baseline (not bursty load)
A8: ☐ | B8: Storage lifecycle: old data tiered to cool/archive; Delta VACUUM with retention
A9: ☐ | B9: Small files compacted (OPTIMIZE); columnar + compression (Parquet/Delta)
A10: ☐ | B10: Egress checked: no needless cross-region / cross-cloud copies; export aggregates
A11: ☐ | B11: Right-sized from a benchmark, not a guess; autoscale floor = steady load
A12: ☐ | B12: Retry storms & runaway backfills bounded
A13: ☐ | B13: Everything tagged (team / pipeline / env) so cost can be attributed
A14: ☐ | B14: Budget + anomaly alert set on spend (Module 6)
A15: ☐ | B15: Cost-vs-SLA tradeoff stated explicitly with the rejected options

Sheet Cloud Compute
A1: Cloud Compute · the VM half — compare Azure / GCP / AWS
A2: Databricks runs on cloud VMs. Pick your cloud's rate and paste it into the Rate Card (VM $/node-hour). Illustrative ~2025, 4 vCPU/16 GB, on-demand region; verify.
A4: Cloud | B4: Instance | C4: On-demand $/hr | D4: Spot $/hr | E4: Reserved/CUD $/hr | F4: Discount notes
A5: Azure | B5: D4s_v5 | C5: 0.192 | D5: =C5*0.1 -> 0.0192 | E5: =C5*0.6 -> 0.1152 | F5: Spot ~-90% · RI ~-72% · Savings Plan ~-65% · no auto SUD
A6: Google Cloud | B6: e2-standard-4 | C6: 0.134 | D6: =C6*0.1 -> 0.0134 | E6: =C6*0.45 -> 0.0603 | F6: Spot ~-91% · CUD ~-55/70% · auto Sustained-Use ~-30%
A7: AWS | B7: m5.xlarge | C7: 0.192 | D7: =C7*0.1 -> 0.0192 | E7: =C7*0.6 -> 0.1152 | F7: Spot ~-90% · RI ~-72% · Savings Plans
A9: Same 4 vCPU / 16 GB spec — GCP ~30% cheaper on-demand here. Always compare like-for-like (vCPU/RAM, region, term).
